LICENSE
MANIFEST.in
README.md
setup.cfg
setup.py
python_singleton.egg-info/PKG-INFO
python_singleton.egg-info/SOURCES.txt
python_singleton.egg-info/dependency_links.txt
python_singleton.egg-info/requires.txt
python_singleton.egg-info/top_level.txt
singleton/__init__.py
tests/__init__.py
tests/tests.py