Metadata-Version: 1.1
Name: python-singleton
Version: 0.1.2
Summary: Singleton Metaclass.
Home-page: https://github.com/romaryd/python-singleton
Author: Romary Dupuis
Author-email: romary@me.com
License: The MIT License (MIT)
